sqli_sentinel/detector.py
sqli_sentinel-0.1.0.dist-info/licenses/LICENSE
sqli_sentinel-0.1.0.dist-info/METADATA
sqli_sentinel-0.1.0.dist-info/WHEEL
sqli_sentinel-0.1.0.dist-info/top_level.txt
sqli_sentinel-0.1.0.dist-info/RECORD
