Metadata-Version: 2.4
Name: sqli-sentinel
Version: 0.1.0
Summary: A hybrid SQL Injection detection tool using Machine Learning and Regex.
Author-email: amiosen <amirhosseinsereshti@gmail.com>
License: MIT
Project-URL: Homepage, https://github.com/amiosen/sqli-sentinel
Project-URL: Issues, https://github.com/amiosen/sqli-sentinel/issues
Classifier: Programming Language :: Python :: 3
Classifier: License :: OSI Approved :: MIT License
Classifier: Operating System :: OS Independent
Classifier: Topic :: Security
Classifier: Topic :: Software Development :: Libraries :: Python Modules
Requires-Python: >=3.8
License-File: LICENSE
Requires-Dist: scikit-learn>=1.0
Requires-Dist: joblib>=1.0
Requires-Dist: pandas>=1.3
Requires-Dist: Django>=3.2
Dynamic: license-file
